pytest_matcher/__init__.py
pytest_matcher/plugin.py
pytest_matcher-2.1.0.dist-info/METADATA
pytest_matcher-2.1.0.dist-info/WHEEL
pytest_matcher-2.1.0.dist-info/entry_points.txt
pytest_matcher-2.1.0.dist-info/RECORD
