Metadata-Version: 2.4
Name: pytest-matcher
Version: 2.1.0
Summary: Easy way to match captured `pytest` output against expectations stored in files
Project-URL: Code, https://github.com/zaufi/pytest-matcher
Project-URL: Documentation, https://pytest-matcher.readthedocs.io
Project-URL: Issues Tracker, https://github.com/zaufi/pytest-matcher/issues
Project-URL: Report an Issue, https://github.com/zaufi/pytest-matcher/issues/new/choose
Author-email: Alex Turbov <zaufi@pm.me>
Maintainer-email: Alex Turbov <zaufi@pm.me>
License:                     GNU GENERAL PUBLIC LICENSE
Keywords: plugin,pytest
Classifier: Development Status :: 5 - Production/Stable
Classifier: Framework :: Pytest
Classifier: Intended Audience :: Developers
Classifier: License :: OSI Approved :: GNU General Public License v3 or later (GPLv3+)
Classifier: Natural Language :: English
Classifier: Operating System :: OS Independent
Classifier: Programming Language :: Python :: 3 :: Only
Classifier: Programming Language :: Python :: 3.10
Classifier: Programming Language :: Python :: 3.11
Classifier: Programming Language :: Python :: 3.12
Classifier: Topic :: Software Development :: Testing
Requires-Python: >=3.10
Requires-Dist: pytest
Requires-Dist: pyyaml
Provides-Extra: pygments
Requires-Dist: pygments; extra == 'pygments'
